{"cabecera":{"tipOperacion":"0101","fecEmision":"2017-05-14","horEmision":"13:25:51","fecVencimiento":"-","codLocalEmisor":"0000","tipDocUsuario":"6","numDocUsuario":"20587896411","rznSocialUsuario":"SERVICABINAS S.A.","tipMoneda":"PEN","sumTotTributos":62675.85,"sumTotValVenta":419779.66,"sumPrecioVenta":423225,"sumDescTotal":59230.51,"sumOtrosCargos":0,"sumTotalAnticipos":0,"sumImpVenta":423225,"ublVersionId":"2.1","customizationId":"2.0"},"detalle":[{"codUnidadMedida":"NIU","ctdUnidadItem":2000,"codProducto":"GLG199","codProductoSUNAT":"52161515","desItem":"Grabadora LG Externo Modelo: GE20LU10","mtoValorUnitario":"83.05","sumTotTributosItem":"26908.47","codTriIGV":"1000","mtoIgvItem":"26908.47","mtoBaseIgvItem":"149491.53","nomTributoIgvItem":"IGV","codTipTributoIgvItem":"VAT","tipAfeIGV":"10","porIgvItem":"18.00","codTriISC":"-","mtoIscItem":"0.00","mtoBaseIscItem":"0.00","nomTributoIscItem":"0.00","codTipTributoIscItem":"0.00","tipSisISC":"0.00","porIscItem":"0.00","codTriOtroItem":"-","mtoTriOtroItem":"0.00","mtoBaseTriOtroItem":"0.00","nomTributoIOtroItem":"0.00","codTipTributoIOtroItem":"0.00","porTriOtroItem":"0.00","mtoPrecioVentaUnitario":"98.00","mtoValorVentaItem":"166101.69","mtoValorReferencialUnitario":"0.00"},{"codUnidadMedida":"NIU","ctdUnidadItem":300,"codProducto":"MVS546","codProductoSUNAT":"43211902","desItem":"Monitor LCD ViewSonic VG2028WM 20","mtoValorUnitario":"525.42","sumTotTributosItem":"24116.95","codTriIGV":"1000","mtoIgvItem":"24116.95","mtoBaseIgvItem":"133983.05","nomTributoIgvItem":"IGV","codTipTributoIgvItem":"VAT","tipAfeIGV":"10","porIgvItem":"18.00","codTriISC":"-","mtoIscItem":"0.00","mtoBaseIscItem":"0.00","nomTributoIscItem":"0.00","codTipTributoIscItem":"0.00","tipSisISC":"0.00","porIscItem":"0.00","codTriOtroItem":"-","mtoTriOtroItem":"0.00","mtoBaseTriOtroItem":"0.00","nomTributoIOtroItem":"0.00","codTipTributoIOtroItem":"0.00","porTriOtroItem":"0.00","mtoPrecioVentaUnitario":"620.00","mtoValorVentaItem":"157627.12","mtoValorReferencialUnitario":"0.00"},{"codUnidadMedida":"NIU","ctdUnidadItem":250,"codProducto":"MPC35","codProductoSUNAT":"43202010","desItem":"Memoria DDR-3 B1333 Kingston","mtoValorUnitario":"52.00","sumTotTributosItem":"0.00","codTriIGV":"9997","mtoIgvItem":"0.00","mtoBaseIgvItem":"13000.00","nomTributoIgvItem":"EXO","codTipTributoIgvItem":"VAT","tipAfeIGV":"20","porIgvItem":"18.00","codTriISC":"-","mtoIscItem":"0.00","mtoBaseIscItem":"0.00","nomTributoIscItem":"0.00","codTipTributoIscItem":"0.00","tipSisISC":"0.00","porIscItem":"0.00","codTriOtroItem":"-","mtoTriOtroItem":"0.00","mtoBaseTriOtroItem":"0.00","nomTributoIOtroItem":"0.00","codTipTributoIOtroItem":"0.00","porTriOtroItem":"0.00","mtoPrecioVentaUnitario":"52.00","mtoValorVentaItem":"13000.00","mtoValorReferencialUnitario":"0.00"},{"codUnidadMedida":"NIU","ctdUnidadItem":500,"codProducto":"TMS22","codProductoSUNAT":"43211706","desItem":"Teclado Microsoft SideWinder X6","mtoValorUnitario":"166.10","sumTotTributosItem":"14949.15","codTriIGV":"1000","mtoIgvItem":"14949.15","mtoBaseIgvItem":"83050.85","nomTributoIgvItem":"IGV","codTipTributoIgvItem":"VAT","tipAfeIGV":"10","porIgvItem":"18.00","codTriISC":"-","mtoIscItem":"0.00","mtoBaseIscItem":"0.00","nomTributoIscItem":"0.00","codTipTributoIscItem":"0.00","tipSisISC":"0.00","porIscItem":"0.00","codTriOtroItem":"-","mtoTriOtroItem":"0.00","mtoBaseTriOtroItem":"0.00","nomTributoIOtroItem":"0.00","codTipTributoIOtroItem":"0.00","porTriOtroItem":"0.00","mtoPrecioVentaUnitario":"196.00","mtoValorVentaItem":"83050.85","mtoValorReferencialUnitario":"0.00"}]}